astpretty.py
astpretty-2.0.0.dist-info/LICENSE
astpretty-2.0.0.dist-info/METADATA
astpretty-2.0.0.dist-info/WHEEL
astpretty-2.0.0.dist-info/entry_points.txt
astpretty-2.0.0.dist-info/top_level.txt
astpretty-2.0.0.dist-info/RECORD
