Metadata-Version: 2.1
Name: astpretty
Version: 2.0.0
Summary: Pretty print the output of python stdlib `ast.parse`.
Home-page: https://github.com/asottile/astpretty
Author: Anthony Sottile
Author-email: asottile@umich.edu
License: MIT
Platform: UNKNOWN
Classifier: License :: OSI Approved :: MIT License
Classifier: Programming Language :: Python :: 3
Classifier: Programming Language :: Python :: 3 :: Only
Classifier: Programming Language :: Python :: 3.6
Classifier: Programming Language :: Python :: 3.7
Classifier: Programming Language :: Python :: 3.8
Classifier: Programming Language :: Python :: Implementation :: CPython
Classifier: Programming Language :: Python :: Implementation :: PyPy
Requires-Python: >=3.6.1
Provides-Extra: typed
Requires-Dist: typed-ast ; extra == 'typed'
